ainft/__init__.py
ainft/chat/__init__.py
ainft/chat/chat.py
ainft/chat/messages.py
ainft/chat/threads.py
ainft/client.py
ainft/exceptions.py
ainft/types.py
ainft/utils.py
ainft_py-0.1.0.dist-info/LICENSE
ainft_py-0.1.0.dist-info/METADATA
ainft_py-0.1.0.dist-info/WHEEL
ainft_py-0.1.0.dist-info/RECORD
