Metadata-Version: 2.1
Name: ainft-py
Version: 0.1.0
Summary: 
License: MIT
Author: AINFT Team
Author-email: dev@ainetwork.ai
Requires-Python: >=3.8,<3.12
Classifier: License :: OSI Approved :: MIT License
Classifier: Programming Language :: Python :: 3
Classifier: Programming Language :: Python :: 3.8
Classifier: Programming Language :: Python :: 3.9
Classifier: Programming Language :: Python :: 3.10
Classifier: Programming Language :: Python :: 3.11
Requires-Dist: ain-py (>=1.0.3,<2.0.0)
Requires-Dist: pydantic (>=2.6.3,<3.0.0)
Requires-Dist: pytest (>=8.1.1,<9.0.0)
